nonebot_plugin_stable_diffusion_diao-0.5.4.9.dist-info/METADATA
nonebot_plugin_stable_diffusion_diao-0.5.4.9.dist-info/WHEEL
nonebot_plugin_stable_diffusion_diao-0.5.4.9.dist-info/entry_points.txt
nonebot_plugin_stable_diffusion_diao-0.5.4.9.dist-info/licenses/LICENSE
nonebot_plugin_stable_diffusion_diao/__init__.py
nonebot_plugin_stable_diffusion_diao/aidraw.py
nonebot_plugin_stable_diffusion_diao/amusement/chatgpt_tagger.py
nonebot_plugin_stable_diffusion_diao/amusement/ramdomgirl.py
nonebot_plugin_stable_diffusion_diao/amusement/today_girl.py
nonebot_plugin_stable_diffusion_diao/amusement/vits.py
nonebot_plugin_stable_diffusion_diao/amusement/wordbank.py
nonebot_plugin_stable_diffusion_diao/backend/__init__.py
nonebot_plugin_stable_diffusion_diao/backend/base.py
nonebot_plugin_stable_diffusion_diao/backend/bing.py
nonebot_plugin_stable_diffusion_diao/backend/mj.py
nonebot_plugin_stable_diffusion_diao/backend/naifu.py
nonebot_plugin_stable_diffusion_diao/backend/novelai.py
nonebot_plugin_stable_diffusion_diao/backend/sd.py
nonebot_plugin_stable_diffusion_diao/config.py
nonebot_plugin_stable_diffusion_diao/config_example.yaml
nonebot_plugin_stable_diffusion_diao/docs/backend.md
nonebot_plugin_stable_diffusion_diao/docs/basic.md
nonebot_plugin_stable_diffusion_diao/docs/mange.md
nonebot_plugin_stable_diffusion_diao/docs/model.md
nonebot_plugin_stable_diffusion_diao/docs/other_gen.md
nonebot_plugin_stable_diffusion_diao/docs/others.md
nonebot_plugin_stable_diffusion_diao/docs/parameter.md
nonebot_plugin_stable_diffusion_diao/docs/plugin.md
nonebot_plugin_stable_diffusion_diao/docs/style.md
nonebot_plugin_stable_diffusion_diao/extension/ADH.md
nonebot_plugin_stable_diffusion_diao/extension/aidraw_help.py
nonebot_plugin_stable_diffusion_diao/extension/anlas.py
nonebot_plugin_stable_diffusion_diao/extension/civitai.py
nonebot_plugin_stable_diffusion_diao/extension/control_net.py
nonebot_plugin_stable_diffusion_diao/extension/daylimit.py
nonebot_plugin_stable_diffusion_diao/extension/deepdanbooru.py
nonebot_plugin_stable_diffusion_diao/extension/explicit_api.py
nonebot_plugin_stable_diffusion_diao/extension/graph.py
nonebot_plugin_stable_diffusion_diao/extension/safe_method.py
nonebot_plugin_stable_diffusion_diao-0.5.4.9.dist-info/RECORD
