Metadata-Version: 2.1
Name: nonebot-plugin-stable-diffusion-diao
Version: 0.5.4.9
Summary: 主要面对stable-diffusion-webui-api的nonebot2插件
Author-Email: DiaoDaiaChan <diaodaiachan@qq.com>
Requires-Dist: aiofiles>=23.1.0
Requires-Dist: aiohttp>=3.8.4
Requires-Dist: nonebot-adapter-onebot>=2.1.3
Requires-Dist: nonebot-adapter-qq
Requires-Dist: nonebot2>=2.0.0b4
Requires-Dist: nonebot-plugin-htmlrender>=0.2.0.3
Requires-Dist: Pillow>=9.5.0
Requires-Dist: qrcode>=7.4.2
Requires-Dist: tqdm
Requires-Dist: redis
Requires-Dist: ruamel.yaml
Requires-Dist: BingImageCreator==0.5.0
Requires-Dist: gradio_client>=0.16.4
Requires-Dist: pydantic
Requires-Dist: stable_diffusion_drawbridge_api>=1.1.3
Requires-Dist: nonebot_plugin_alconna
Requires-Dist: bs4
